twisp/__init__.py
twisp/__main__.py
twisp/tsib.py
twisp/utils.py
twisp-0.1.0.dist-info/entry_points.txt
twisp-0.1.0.dist-info/LICENSE
twisp-0.1.0.dist-info/WHEEL
twisp-0.1.0.dist-info/METADATA
twisp-0.1.0.dist-info/RECORD
