Metadata-Version: 2.1
Name: twisp
Version: 0.1.0
Summary: 
License: MIT
Author: Tzeng Yuxio
Author-email: tzengyuxio@gmail.com
Maintainer: Tzeng Yuxio
Maintainer-email: tzengyuxio@gmail.com
Requires-Python: >=3.6,<4.0
Classifier: License :: OSI Approved :: MIT License
Classifier: Programming Language :: Python :: 3
Classifier: Programming Language :: Python :: 3.6
Classifier: Programming Language :: Python :: 3.7
Classifier: Programming Language :: Python :: 3.8
Classifier: Programming Language :: Python :: 3.9
Requires-Dist: tika (>=1.24,<2.0)
